streamlit_text_rating/__init__.py
streamlit_text_rating/st_text_rater.py
streamlit_text_rating/version.py
streamlit_text_rating/frontend/build/asset-manifest.json
streamlit_text_rating/frontend/build/bootstrap.min.css
streamlit_text_rating/frontend/build/dislike.png
streamlit_text_rating/frontend/build/index.html
streamlit_text_rating/frontend/build/like-button.png
streamlit_text_rating/frontend/build/precache-manifest.edaef938dc2f55aa4d91c5413fdbccb7.js
streamlit_text_rating/frontend/build/service-worker.js
streamlit_text_rating/frontend/build/thumbsup.svg
streamlit_text_rating/frontend/build/static/js/2.9f915b55.chunk.js
streamlit_text_rating/frontend/build/static/js/2.9f915b55.chunk.js.LICENSE.txt
streamlit_text_rating/frontend/build/static/js/2.9f915b55.chunk.js.map
streamlit_text_rating/frontend/build/static/js/main.6b1a4200.chunk.js
streamlit_text_rating/frontend/build/static/js/main.6b1a4200.chunk.js.map
streamlit_text_rating/frontend/build/static/js/runtime-main.11ec9aca.js
streamlit_text_rating/frontend/build/static/js/runtime-main.11ec9aca.js.map
streamlit_text_rating-0.1.5.dist-info/METADATA
streamlit_text_rating-0.1.5.dist-info/WHEEL
streamlit_text_rating-0.1.5.dist-info/top_level.txt
streamlit_text_rating-0.1.5.dist-info/RECORD
