Metadata-Version: 2.1
Name: streamlit-text-rating
Version: 0.1.5
Summary: streamlit_text_ratings enables you to rate the text data
Home-page: https://github.com/TVS-Motor-Company/streamlit-text-rating
Author: Ashish Rai, Naga Budigam
Author-email: ashishraics512@gmail.com, nagaraju.iiit@gmail.com
License: MIT
Platform: UNKNOWN
Classifier: License :: OSI Approved :: MIT License
Classifier: Programming Language :: Python :: 3
Classifier: Programming Language :: Python :: 3.7
Classifier: Programming Language :: Python :: 3.8
Requires-Python: >=3.6
Requires-Dist: streamlit (>=1.0.0)
